wscm.py
whitesky_cloud_migrator-0.4.0.dist-info/LICENSE
whitesky_cloud_migrator-0.4.0.dist-info/METADATA
whitesky_cloud_migrator-0.4.0.dist-info/WHEEL
whitesky_cloud_migrator-0.4.0.dist-info/entry_points.txt
whitesky_cloud_migrator-0.4.0.dist-info/top_level.txt
whitesky_cloud_migrator-0.4.0.dist-info/RECORD
