Metadata-Version: 2.1
Name: whitesky-cloud-migrator
Version: 0.4.0
Summary: A Python program to migrate servers to whitesky.cloud
Home-page: https://whitesky.cloud
Author: Geert Audenaert
Author-email: geert.audenaert@whitesky.cloud
Classifier: Programming Language :: Python :: 3
Classifier: License :: OSI Approved :: MIT License
Classifier: Operating System :: OS Independent
Requires-Python: >=3.8
License-File: LICENSE
Requires-Dist: blessed ==1.20.0
Requires-Dist: certifi ==2024.2.2
Requires-Dist: charset-normalizer ==3.3.2
Requires-Dist: click ==8.1.7
Requires-Dist: editor ==1.6.6
Requires-Dist: gitdb ==4.0.11
Requires-Dist: GitPython ==3.1.41
Requires-Dist: idna ==3.7
Requires-Dist: inquirer ==3.2.4
Requires-Dist: readchar ==4.1.0
Requires-Dist: requests ==2.32.2
Requires-Dist: runs ==1.2.2
Requires-Dist: setuptools ==69.0.3
Requires-Dist: six ==1.16.0
Requires-Dist: smmap ==5.0.1
Requires-Dist: urllib3 ==2.2.1
Requires-Dist: wcwidth ==0.2.13
Requires-Dist: wheel ==0.43.0
Requires-Dist: xmod ==1.8.1
